{
  "gameMode": "Classic",
  "difficulty": "Normal",
  "level": 95,
  "category": 0,
  "time": 60,
  "levelName": "Level_95",
  "grid": {
    "rows": 5,
    "columns": 5,
    "cells": [
      {
        "row": 0,
        "column": 0,
        "entity": {
          "type": "Shooter",
          "entityId": "entity_s_0_0_z14e",
          "blocksPath": true,
          "shooter": {
            "shooterId": "s_0_0_z14e",
            "colorId": "Blue",
            "capacity": 9,
            "modifiers": []
          }
        }
      },
      {
        "row": 0,
        "column": 1,
        "entity": {
          "type": "Shooter",
          "entityId": "entity_s_0_1_q7bt",
          "blocksPath": true,
          "shooter": {
            "shooterId": "s_0_1_q7bt",
            "colorId": "Blue",
            "capacity": 9,
            "modifiers": []
          }
        }
      },
      {
        "row": 0,
        "column": 2,
        "entity": {
          "type": "Shooter",
          "entityId": "entity_s_0_2_gvaj",
          "blocksPath": true,
          "shooter": {
            "shooterId": "s_0_2_gvaj",
            "colorId": "Blue",
            "capacity": 9,
            "modifiers": []
          }
        }
      },
      {
        "row": 0,
        "column": 3,
        "entity": {
          "type": "Shooter",
          "entityId": "entity_s_0_3_nt5b",
          "blocksPath": true,
          "shooter": {
            "shooterId": "s_0_3_nt5b",
            "colorId": "Blue",
            "capacity": 9,
            "modifiers": []
          }
        }
      },
      {
        "row": 0,
        "column": 4,
        "entity": {
          "type": "Shooter",
          "entityId": "entity_s_0_4_wzu4",
          "blocksPath": true,
          "shooter": {
            "shooterId": "s_0_4_wzu4",
            "colorId": "Blue",
            "capacity": 9,
            "modifiers": []
          }
        }
      },
      {
        "row": 1,
        "column": 0,
        "entity": {
          "type": "Shooter",
          "entityId": "entity_s_1_0_y4ad",
          "blocksPath": true,
          "shooter": {
            "shooterId": "s_1_0_y4ad",
            "colorId": "Blue",
            "capacity": 9,
            "modifiers": []
          }
        }
      },
      {
        "row": 1,
        "column": 1,
        "entity": {
          "type": "Shooter",
          "entityId": "entity_s_1_1_cj74",
          "blocksPath": true,
          "shooter": {
            "shooterId": "s_1_1_cj74",
            "colorId": "Purple",
            "capacity": 9,
            "modifiers": []
          }
        }
      },
      {
        "row": 1,
        "column": 2,
        "entity": {
          "type": "Shooter",
          "entityId": "entity_s_1_2_jlop",
          "blocksPath": true,
          "shooter": {
            "shooterId": "s_1_2_jlop",
            "colorId": "Purple",
            "capacity": 9,
            "modifiers": []
          }
        }
      },
      {
        "row": 1,
        "column": 3,
        "entity": {
          "type": "Shooter",
          "entityId": "entity_s_1_3_xkru",
          "blocksPath": true,
          "shooter": {
            "shooterId": "s_1_3_xkru",
            "colorId": "Purple",
            "capacity": 9,
            "modifiers": []
          }
        }
      },
      {
        "row": 1,
        "column": 4,
        "entity": {
          "type": "Shooter",
          "entityId": "entity_s_1_4_x9d1",
          "blocksPath": true,
          "shooter": {
            "shooterId": "s_1_4_x9d1",
            "colorId": "Blue",
            "capacity": 9,
            "modifiers": []
          }
        }
      },
      {
        "row": 2,
        "column": 0,
        "entity": {
          "type": "Shooter",
          "entityId": "entity_s_2_0_mgx3",
          "blocksPath": true,
          "shooter": {
            "shooterId": "s_2_0_mgx3",
            "colorId": "Blue",
            "capacity": 9,
            "modifiers": []
          }
        }
      },
      {
        "row": 2,
        "column": 1,
        "entity": {
          "type": "Shooter",
          "entityId": "entity_s_2_1_kv06",
          "blocksPath": true,
          "shooter": {
            "shooterId": "s_2_1_kv06",
            "colorId": "Purple",
            "capacity": 9,
            "modifiers": []
          }
        }
      },
      {
        "row": 2,
        "column": 2,
        "entity": {
          "type": "Shooter",
          "entityId": "entity_s_2_2_w1fg",
          "blocksPath": true,
          "shooter": {
            "shooterId": "s_2_2_w1fg",
            "colorId": "Red",
            "capacity": 9,
            "modifiers": []
          }
        }
      },
      {
        "row": 2,
        "column": 3,
        "entity": {
          "type": "Shooter",
          "entityId": "entity_s_2_3_xqo6",
          "blocksPath": true,
          "shooter": {
            "shooterId": "s_2_3_xqo6",
            "colorId": "Purple",
            "capacity": 9,
            "modifiers": []
          }
        }
      },
      {
        "row": 2,
        "column": 4,
        "entity": {
          "type": "Shooter",
          "entityId": "entity_s_2_4_8nrg",
          "blocksPath": true,
          "shooter": {
            "shooterId": "s_2_4_8nrg",
            "colorId": "Blue",
            "capacity": 9,
            "modifiers": []
          }
        }
      },
      {
        "row": 3,
        "column": 0,
        "entity": {
          "type": "Shooter",
          "entityId": "entity_s_3_0_o22m",
          "blocksPath": true,
          "shooter": {
            "shooterId": "s_3_0_o22m",
            "colorId": "Blue",
            "capacity": 9,
            "modifiers": []
          }
        }
      },
      {
        "row": 3,
        "column": 1,
        "entity": {
          "type": "Shooter",
          "entityId": "entity_s_3_1_mqn7",
          "blocksPath": true,
          "shooter": {
            "shooterId": "s_3_1_mqn7",
            "colorId": "Purple",
            "capacity": 9,
            "modifiers": []
          }
        }
      },
      {
        "row": 3,
        "column": 2,
        "entity": {
          "type": "Shooter",
          "entityId": "entity_s_3_2_jlxn",
          "blocksPath": true,
          "shooter": {
            "shooterId": "s_3_2_jlxn",
            "colorId": "Purple",
            "capacity": 9,
            "modifiers": []
          }
        }
      },
      {
        "row": 3,
        "column": 3,
        "entity": {
          "type": "Shooter",
          "entityId": "entity_s_3_3_ldk6",
          "blocksPath": true,
          "shooter": {
            "shooterId": "s_3_3_ldk6",
            "colorId": "Purple",
            "capacity": 9,
            "modifiers": []
          }
        }
      },
      {
        "row": 3,
        "column": 4,
        "entity": {
          "type": "Shooter",
          "entityId": "entity_s_3_4_9r1z",
          "blocksPath": true,
          "shooter": {
            "shooterId": "s_3_4_9r1z",
            "colorId": "Blue",
            "capacity": 9,
            "modifiers": []
          }
        }
      },
      {
        "row": 4,
        "column": 0,
        "entity": {
          "type": "Shooter",
          "entityId": "entity_s_4_0_b4o6",
          "blocksPath": true,
          "shooter": {
            "shooterId": "s_4_0_b4o6",
            "colorId": "Blue",
            "capacity": 9,
            "modifiers": []
          }
        }
      },
      {
        "row": 4,
        "column": 1,
        "entity": {
          "type": "Shooter",
          "entityId": "entity_s_4_1_qls9",
          "blocksPath": true,
          "shooter": {
            "shooterId": "s_4_1_qls9",
            "colorId": "Blue",
            "capacity": 9,
            "modifiers": []
          }
        }
      },
      {
        "row": 4,
        "column": 2,
        "entity": {
          "type": "Shooter",
          "entityId": "entity_s_4_2_bv2m",
          "blocksPath": true,
          "shooter": {
            "shooterId": "s_4_2_bv2m",
            "colorId": "Blue",
            "capacity": 9,
            "modifiers": []
          }
        }
      },
      {
        "row": 4,
        "column": 3,
        "entity": {
          "type": "Shooter",
          "entityId": "entity_s_4_3_6mwa",
          "blocksPath": true,
          "shooter": {
            "shooterId": "s_4_3_6mwa",
            "colorId": "Blue",
            "capacity": 9,
            "modifiers": []
          }
        }
      },
      {
        "row": 4,
        "column": 4,
        "entity": {
          "type": "Shooter",
          "entityId": "entity_s_4_4_p041",
          "blocksPath": true,
          "shooter": {
            "shooterId": "s_4_4_p041",
            "colorId": "Blue",
            "capacity": 9,
            "modifiers": []
          }
        }
      }
    ],
    "obstacles": [],
    "shooterGroups": []
  },
  "gateSystem": {
    "gateCount": 4,
    "maxVisibleTrayPerGate": 4,
    "gates": [
      {
        "gateIndex": 0,
        "trayQueue": [
          {
            "trayId": "t_jiw8",
            "layers": [
              {
                "colorId": "Blue",
                "requiredCount": 3
              }
            ]
          },
          {
            "trayId": "t_w7n4",
            "layers": [
              {
                "colorId": "Blue",
                "requiredCount": 3
              }
            ]
          },
          {
            "trayId": "t_euke",
            "layers": [
              {
                "colorId": "Blue",
                "requiredCount": 3
              }
            ]
          },
          {
            "trayId": "t_a1xv",
            "layers": [
              {
                "colorId": "Purple",
                "requiredCount": 3
              }
            ]
          },
          {
            "trayId": "t_ri9i",
            "layers": [
              {
                "colorId": "Blue",
                "requiredCount": 3
              }
            ]
          },
          {
            "trayId": "t_2dmq",
            "layers": [
              {
                "colorId": "Blue",
                "requiredCount": 3
              }
            ]
          },
          {
            "trayId": "t_v7n6",
            "layers": [
              {
                "colorId": "Blue",
                "requiredCount": 3
              }
            ]
          },
          {
            "trayId": "t_lgdc",
            "layers": [
              {
                "colorId": "Blue",
                "requiredCount": 3
              }
            ]
          },
          {
            "trayId": "t_hd98",
            "layers": [
              {
                "colorId": "Blue",
                "requiredCount": 3
              }
            ]
          },
          {
            "trayId": "t_y9rq",
            "layers": [
              {
                "colorId": "Purple",
                "requiredCount": 3
              }
            ]
          },
          {
            "trayId": "t_qkcc",
            "layers": [
              {
                "colorId": "Purple",
                "requiredCount": 3
              }
            ]
          },
          {
            "trayId": "t_ythr",
            "layers": [
              {
                "colorId": "Blue",
                "requiredCount": 3
              }
            ]
          },
          {
            "trayId": "t_mu7x",
            "layers": [
              {
                "colorId": "Blue",
                "requiredCount": 3
              }
            ]
          },
          {
            "trayId": "t_cchc",
            "layers": [
              {
                "colorId": "Blue",
                "requiredCount": 3
              }
            ]
          },
          {
            "trayId": "t_gydi",
            "layers": [
              {
                "colorId": "Blue",
                "requiredCount": 3
              }
            ]
          },
          {
            "trayId": "t_gtvf",
            "layers": [
              {
                "colorId": "Blue",
                "requiredCount": 3
              }
            ]
          },
          {
            "trayId": "t_x2ow",
            "layers": [
              {
                "colorId": "Blue",
                "requiredCount": 3
              }
            ]
          },
          {
            "trayId": "t_3t34",
            "layers": [
              {
                "colorId": "Blue",
                "requiredCount": 3
              }
            ]
          },
          {
            "trayId": "t_u102",
            "layers": [
              {
                "colorId": "Blue",
                "requiredCount": 3
              }
            ]
          }
        ]
      },
      {
        "gateIndex": 1,
        "trayQueue": [
          {
            "trayId": "t_h7p9",
            "layers": [
              {
                "colorId": "Red",
                "requiredCount": 3
              }
            ]
          },
          {
            "trayId": "t_0voq",
            "layers": [
              {
                "colorId": "Blue",
                "requiredCount": 3
              }
            ]
          },
          {
            "trayId": "t_irc1",
            "layers": [
              {
                "colorId": "Blue",
                "requiredCount": 3
              }
            ]
          },
          {
            "trayId": "t_y63e",
            "layers": [
              {
                "colorId": "Blue",
                "requiredCount": 3
              }
            ]
          },
          {
            "trayId": "t_xmsd",
            "layers": [
              {
                "colorId": "Blue",
                "requiredCount": 3
              }
            ]
          },
          {
            "trayId": "t_n3x6",
            "layers": [
              {
                "colorId": "Blue",
                "requiredCount": 3
              }
            ]
          },
          {
            "trayId": "t_klq8",
            "layers": [
              {
                "colorId": "Purple",
                "requiredCount": 3
              }
            ]
          },
          {
            "trayId": "t_7hvs",
            "layers": [
              {
                "colorId": "Purple",
                "requiredCount": 3
              }
            ]
          },
          {
            "trayId": "t_kodj",
            "layers": [
              {
                "colorId": "Blue",
                "requiredCount": 3
              }
            ]
          },
          {
            "trayId": "t_kmo8",
            "layers": [
              {
                "colorId": "Blue",
                "requiredCount": 3
              }
            ]
          },
          {
            "trayId": "t_kxnz",
            "layers": [
              {
                "colorId": "Blue",
                "requiredCount": 3
              }
            ]
          },
          {
            "trayId": "t_m949",
            "layers": [
              {
                "colorId": "Blue",
                "requiredCount": 3
              }
            ]
          },
          {
            "trayId": "t_g5v2",
            "layers": [
              {
                "colorId": "Blue",
                "requiredCount": 3
              }
            ]
          },
          {
            "trayId": "t_rp26",
            "layers": [
              {
                "colorId": "Purple",
                "requiredCount": 3
              }
            ]
          },
          {
            "trayId": "t_qm8z",
            "layers": [
              {
                "colorId": "Red",
                "requiredCount": 3
              }
            ]
          },
          {
            "trayId": "t_22nf",
            "layers": [
              {
                "colorId": "Purple",
                "requiredCount": 3
              }
            ]
          },
          {
            "trayId": "t_yckq",
            "layers": [
              {
                "colorId": "Blue",
                "requiredCount": 3
              }
            ]
          },
          {
            "trayId": "t_htjr",
            "layers": [
              {
                "colorId": "Purple",
                "requiredCount": 3
              }
            ]
          },
          {
            "trayId": "t_7k2b",
            "layers": [
              {
                "colorId": "Blue",
                "requiredCount": 3
              }
            ]
          }
        ]
      },
      {
        "gateIndex": 2,
        "trayQueue": [
          {
            "trayId": "t_nket",
            "layers": [
              {
                "colorId": "Purple",
                "requiredCount": 3
              }
            ]
          },
          {
            "trayId": "t_kunl",
            "layers": [
              {
                "colorId": "Purple",
                "requiredCount": 3
              }
            ]
          },
          {
            "trayId": "t_ezm7",
            "layers": [
              {
                "colorId": "Purple",
                "requiredCount": 3
              }
            ]
          },
          {
            "trayId": "t_790h",
            "layers": [
              {
                "colorId": "Blue",
                "requiredCount": 3
              }
            ]
          },
          {
            "trayId": "t_bdfa",
            "layers": [
              {
                "colorId": "Purple",
                "requiredCount": 3
              }
            ]
          },
          {
            "trayId": "t_pkfd",
            "layers": [
              {
                "colorId": "Blue",
                "requiredCount": 3
              }
            ]
          },
          {
            "trayId": "t_7drq",
            "layers": [
              {
                "colorId": "Purple",
                "requiredCount": 3
              }
            ]
          },
          {
            "trayId": "t_9qcs",
            "layers": [
              {
                "colorId": "Blue",
                "requiredCount": 3
              }
            ]
          },
          {
            "trayId": "t_y2pr",
            "layers": [
              {
                "colorId": "Blue",
                "requiredCount": 3
              }
            ]
          },
          {
            "trayId": "t_mrhx",
            "layers": [
              {
                "colorId": "Purple",
                "requiredCount": 3
              }
            ]
          },
          {
            "trayId": "t_7o6q",
            "layers": [
              {
                "colorId": "Blue",
                "requiredCount": 3
              }
            ]
          },
          {
            "trayId": "t_03sx",
            "layers": [
              {
                "colorId": "Blue",
                "requiredCount": 3
              }
            ]
          },
          {
            "trayId": "t_4ml4",
            "layers": [
              {
                "colorId": "Purple",
                "requiredCount": 3
              }
            ]
          },
          {
            "trayId": "t_2svc",
            "layers": [
              {
                "colorId": "Blue",
                "requiredCount": 3
              }
            ]
          },
          {
            "trayId": "t_gexj",
            "layers": [
              {
                "colorId": "Blue",
                "requiredCount": 3
              }
            ]
          },
          {
            "trayId": "t_coje",
            "layers": [
              {
                "colorId": "Blue",
                "requiredCount": 3
              }
            ]
          },
          {
            "trayId": "t_q5jr",
            "layers": [
              {
                "colorId": "Blue",
                "requiredCount": 3
              }
            ]
          },
          {
            "trayId": "t_y204",
            "layers": [
              {
                "colorId": "Purple",
                "requiredCount": 3
              }
            ]
          },
          {
            "trayId": "t_uzo3",
            "layers": [
              {
                "colorId": "Purple",
                "requiredCount": 3
              }
            ]
          }
        ]
      },
      {
        "gateIndex": 3,
        "trayQueue": [
          {
            "trayId": "t_xgg4",
            "layers": [
              {
                "colorId": "Blue",
                "requiredCount": 3
              }
            ]
          },
          {
            "trayId": "t_rdpd",
            "layers": [
              {
                "colorId": "Purple",
                "requiredCount": 3
              }
            ]
          },
          {
            "trayId": "t_80n2",
            "layers": [
              {
                "colorId": "Red",
                "requiredCount": 3
              }
            ]
          },
          {
            "trayId": "t_ga0o",
            "layers": [
              {
                "colorId": "Purple",
                "requiredCount": 3
              }
            ]
          },
          {
            "trayId": "t_kcc2",
            "layers": [
              {
                "colorId": "Blue",
                "requiredCount": 3
              }
            ]
          },
          {
            "trayId": "t_h4ga",
            "layers": [
              {
                "colorId": "Purple",
                "requiredCount": 3
              }
            ]
          },
          {
            "trayId": "t_gs6k",
            "layers": [
              {
                "colorId": "Blue",
                "requiredCount": 3
              }
            ]
          },
          {
            "trayId": "t_4w9e",
            "layers": [
              {
                "colorId": "Blue",
                "requiredCount": 3
              }
            ]
          },
          {
            "trayId": "t_9ijd",
            "layers": [
              {
                "colorId": "Blue",
                "requiredCount": 3
              }
            ]
          },
          {
            "trayId": "t_mpoe",
            "layers": [
              {
                "colorId": "Purple",
                "requiredCount": 3
              }
            ]
          },
          {
            "trayId": "t_q8ce",
            "layers": [
              {
                "colorId": "Purple",
                "requiredCount": 3
              }
            ]
          },
          {
            "trayId": "t_a7z0",
            "layers": [
              {
                "colorId": "Blue",
                "requiredCount": 3
              }
            ]
          },
          {
            "trayId": "t_wh41",
            "layers": [
              {
                "colorId": "Blue",
                "requiredCount": 3
              }
            ]
          },
          {
            "trayId": "t_u8eh",
            "layers": [
              {
                "colorId": "Blue",
                "requiredCount": 3
              }
            ]
          },
          {
            "trayId": "t_dg3h",
            "layers": [
              {
                "colorId": "Blue",
                "requiredCount": 3
              }
            ]
          },
          {
            "trayId": "t_wd68",
            "layers": [
              {
                "colorId": "Purple",
                "requiredCount": 3
              }
            ]
          },
          {
            "trayId": "t_711o",
            "layers": [
              {
                "colorId": "Purple",
                "requiredCount": 3
              }
            ]
          },
          {
            "trayId": "t_7v6p",
            "layers": [
              {
                "colorId": "Blue",
                "requiredCount": 3
              }
            ]
          }
        ]
      }
    ]
  }
}